wtbox/__init__.py
wtbox/_ff_metabo_config.py
wtbox/_fix_inspector_bug.py
wtbox/_iso_corr.py
wtbox/_local_feature_finder.py
wtbox/_lowess.py
wtbox/_multiprocess.py
wtbox/_rt_align.py
wtbox/_shift_rt_windows.py
wtbox/app.py
wtbox/checks_and_settings.py
wtbox/collect_and_lookup.py
wtbox/default_guis.py
wtbox/default_plotting.py
wtbox/dli_rt_align.py
wtbox/doc.py
wtbox/feature_analysis.py
wtbox/feature_extraction.py
wtbox/fitting.py
wtbox/in_out.py
wtbox/integrate_smoothed_emg.py
wtbox/mf_utils.py
wtbox/minimal_module.py
wtbox/peakmap_operations.py
wtbox/subtract_peak_tables.py
wtbox/table_operations.py
wtbox/utils.py
wtbox/docs/workflow_documentation_-E7450-2D6LM32.htm
wtbox/docs/workflow_documentation_.htm
wtbox-0.0.54.dist-info/LICENSE
wtbox-0.0.54.dist-info/METADATA
wtbox-0.0.54.dist-info/PKG-INFO-E7450-2D6LM32
wtbox-0.0.54.dist-info/PKG-INFO-E7450-2D6LM32-1
wtbox-0.0.54.dist-info/SOURCES-E7450-2D6LM32-1.txt
wtbox-0.0.54.dist-info/SOURCES-E7450-2D6LM32.txt
wtbox-0.0.54.dist-info/WHEEL
wtbox-0.0.54.dist-info/entry_points.txt
wtbox-0.0.54.dist-info/top_level.txt
wtbox-0.0.54.dist-info/RECORD
